{
  "Info": [
    {
      "IsSuccess": "True",
      "InAddress": "基隆市七堵區永安里崇孝街俊德吊橋頭V",
      "InSRS": "EPSG:4326",
      "InFuzzyType": "[單雙號機制]+[最近門牌號機制]",
      "InFuzzyBuffer": "0",
      "InIsOnlyFullMatch": "False",
      "InIsLockCounty": "True",
      "InIsLockTown": "False",
      "InIsLockVillage": "False",
      "InIsLockRoadSection": "False",
      "InIsLockLane": "False",
      "InIsLockAlley": "False",
      "InIsLockArea": "False",
      "InIsSameNumber_SubNumber": "True",
      "InCanIgnoreVillage": "True",
      "InCanIgnoreNeighborhood": "True",
      "InReturnMaxCount": "0",
      "OutTotal": "104",
      "OutMatchType": "模糊比對",
      "OutMatchCode": "[基隆市]\tT:1,V:1,R:1,S:-1,L:-1,A:-1,SA:-1,T:-1,AR:-1,NO:-1,E:-1,N:-1",
      "OutTraceInfo": "[基隆市]\t { 模糊比對 } (七堵區)\t找到符合的[鄉鎮市區]，(永安里)\t找到符合的[村里]，(崇孝街)\t找到符合的[路街名]，模糊比對找到 104 筆符合的門牌地址。( 限制回傳 10 筆門牌地址 )"
    }
  ],
  "AddressList": [
    {
      "FULL_ADDR": "基隆市七堵區永安里8鄰崇孝街1號",
      "COUNTY": "基隆市",
      "TOWN": "七堵區",
      "VILLAGE": "永安里",
      "NEIGHBORHOOD": "8鄰",
      "ROAD": "崇孝街",
      "SECTION": "",
      "LANE": "",
      "ALLEY": "",
      "SUB_ALLEY": "",
      "TONG": "",
      "AREA": "",
      "NUMBER": "1號",
      "X": 121.710539,
      "Y": 25.096869
    },
    {
      "FULL_ADDR": "基隆市七堵區永安里1鄰崇孝街2號",
      "COUNTY": "基隆市",
      "TOWN": "七堵區",
      "VILLAGE": "永安里",
      "NEIGHBORHOOD": "1鄰",
      "ROAD": "崇孝街",
      "SECTION": "",
      "LANE": "",
      "ALLEY": "",
      "SUB_ALLEY": "",
      "TONG": "",
      "AREA": "",
      "NUMBER": "2號",
      "X": 121.710539,
      "Y": 25.097249
    },
    {
      "FULL_ADDR": "基隆市七堵區永安里1鄰崇孝街2之1號",
      "COUNTY": "基隆市",
      "TOWN": "七堵區",
      "VILLAGE": "永安里",
      "NEIGHBORHOOD": "1鄰",
      "ROAD": "崇孝街",
      "SECTION": "",
      "LANE": "",
      "ALLEY": "",
      "SUB_ALLEY": "",
      "TONG": "",
      "AREA": "",
      "NUMBER": "2之1號",
      "X": 121.710576,
      "Y": 25.097365
    },
    {
      "FULL_ADDR": "基隆市七堵區永安里12鄰崇孝街6號",
      "COUNTY": "基隆市",
      "TOWN": "七堵區",
      "VILLAGE": "永安里",
      "NEIGHBORHOOD": "12鄰",
      "ROAD": "崇孝街",
      "SECTION": "",
      "LANE": "",
      "ALLEY": "",
      "SUB_ALLEY": "",
      "TONG": "",
      "AREA": "",
      "NUMBER": "6號",
      "X": 121.710466,
      "Y": 25.097549
    },
    {
      "FULL_ADDR": "基隆市七堵區永安里8鄰崇孝街6之1號",
      "COUNTY": "基隆市",
      "TOWN": "七堵區",
      "VILLAGE": "永安里",
      "NEIGHBORHOOD": "8鄰",
      "ROAD": "崇孝街",
      "SECTION": "",
      "LANE": "",
      "ALLEY": "",
      "SUB_ALLEY": "",
      "TONG": "",
      "AREA": "",
      "NUMBER": "6之1號",
      "X": 121.709709,
      "Y": 25.096647
    },
    {
      "FULL_ADDR": "基隆市七堵區永安里8鄰崇孝街11之2號",
      "COUNTY": "基隆市",
      "TOWN": "七堵區",
      "VILLAGE": "永安里",
      "NEIGHBORHOOD": "8鄰",
      "ROAD": "崇孝街",
      "SECTION": "",
      "LANE": "",
      "ALLEY": "",
      "SUB_ALLEY": "",
      "TONG": "",
      "AREA": "",
      "NUMBER": "11之2號",
      "X": 121.709698,
      "Y": 25.097733
    },
    {
      "FULL_ADDR": "基隆市七堵區永安里8鄰崇孝街11之3號",
      "COUNTY": "基隆市",
      "TOWN": "七堵區",
      "VILLAGE": "永安里",
      "NEIGHBORHOOD": "8鄰",
      "ROAD": "崇孝街",
      "SECTION": "",
      "LANE": "",
      "ALLEY": "",
      "SUB_ALLEY": "",
      "TONG": "",
      "AREA": "",
      "NUMBER": "11之3號",
      "X": 121.709573,
      "Y": 25.097723
    },
    {
      "FULL_ADDR": "基隆市七堵區永安里8鄰崇孝街11之4號",
      "COUNTY": "基隆市",
      "TOWN": "七堵區",
      "VILLAGE": "永安里",
      "NEIGHBORHOOD": "8鄰",
      "ROAD": "崇孝街",
      "SECTION": "",
      "LANE": "",
      "ALLEY": "",
      "SUB_ALLEY": "",
      "TONG": "",
      "AREA": "",
      "NUMBER": "11之4號",
      "X": 121.709841,
      "Y": 25.097791
    },
    {
      "FULL_ADDR": "基隆市七堵區永安里8鄰崇孝街11之5號",
      "COUNTY": "基隆市",
      "TOWN": "七堵區",
      "VILLAGE": "永安里",
      "NEIGHBORHOOD": "8鄰",
      "ROAD": "崇孝街",
      "SECTION": "",
      "LANE": "",
      "ALLEY": "",
      "SUB_ALLEY": "",
      "TONG": "",
      "AREA": "",
      "NUMBER": "11之5號",
      "X": 121.709770,
      "Y": 25.097743
    },
    {
      "FULL_ADDR": "基隆市七堵區永安里8鄰崇孝街11之6號",
      "COUNTY": "基隆市",
      "TOWN": "七堵區",
      "VILLAGE": "永安里",
      "NEIGHBORHOOD": "8鄰",
      "ROAD": "崇孝街",
      "SECTION": "",
      "LANE": "",
      "ALLEY": "",
      "SUB_ALLEY": "",
      "TONG": "",
      "AREA": "",
      "NUMBER": "11之6號",
      "X": 121.709748,
      "Y": 25.097764
    }
  ]
}