{
  "Info": [
    {
      "IsSuccess": "True",
      "InAddress": "桃園市大園區大仁46號3樓",
      "InSRS": "EPSG:4326",
      "InFuzzyType": "[單雙號機制]+[最近門牌號機制]",
      "InFuzzyBuffer": "0",
      "InIsOnlyFullMatch": "False",
      "InIsLockCounty": "True",
      "InIsLockTown": "False",
      "InIsLockVillage": "False",
      "InIsLockRoadSection": "False",
      "InIsLockLane": "False",
      "InIsLockAlley": "False",
      "InIsLockArea": "False",
      "InIsSameNumber_SubNumber": "True",
      "InCanIgnoreVillage": "True",
      "InCanIgnoreNeighborhood": "True",
      "InReturnMaxCount": "0",
      "OutTotal": "54",
      "OutMatchType": "模糊比對",
      "OutMatchCode": "[桃園市]\tT:1,V:-1,R:-1,S:-1,L:-1,A:-1,SA:-1,T:-1,AR:0,NO:1,E:-1,N:-1",
      "OutTraceInfo": "[桃園市]\t { 模糊比對 } (大園區)\t找到符合的[鄉鎮市區]，(大仁)\t找不到符合的[地區]，轉換搜尋找不到符合的[地區]，(46號)\t找到符合的[門牌號碼]，進行[雙號過濾]，模糊比對找到 54 筆符合的門牌地址。( 限制回傳 10 筆門牌地址 )"
    }
  ],
  "AddressList": [
    {
      "FULL_ADDR": "桃園市大園區北港里16鄰自立四街46號",
      "COUNTY": "桃園市",
      "TOWN": "大園區",
      "VILLAGE": "北港里",
      "NEIGHBORHOOD": "16鄰",
      "ROAD": "自立四街",
      "SECTION": "",
      "LANE": "",
      "ALLEY": "",
      "SUB_ALLEY": "",
      "TONG": "",
      "AREA": "",
      "NUMBER": "46號",
      "X": 121.182605,
      "Y": 25.065401
    },
    {
      "FULL_ADDR": "桃園市大園區菓林里21鄰復興街46號",
      "COUNTY": "桃園市",
      "TOWN": "大園區",
      "VILLAGE": "菓林里",
      "NEIGHBORHOOD": "21鄰",
      "ROAD": "復興街",
      "SECTION": "",
      "LANE": "",
      "ALLEY": "",
      "SUB_ALLEY": "",
      "TONG": "",
      "AREA": "",
      "NUMBER": "46號",
      "X": 121.255649,
      "Y": 25.087558
    },
    {
      "FULL_ADDR": "桃園市大園區大園里21鄰民生路46號",
      "COUNTY": "桃園市",
      "TOWN": "大園區",
      "VILLAGE": "大園里",
      "NEIGHBORHOOD": "21鄰",
      "ROAD": "民生路",
      "SECTION": "",
      "LANE": "",
      "ALLEY": "",
      "SUB_ALLEY": "",
      "TONG": "",
      "AREA": "",
      "NUMBER": "46號",
      "X": 121.199290,
      "Y": 25.068940
    },
    {
      "FULL_ADDR": "桃園市大園區大園里8鄰中山南路46號",
      "COUNTY": "桃園市",
      "TOWN": "大園區",
      "VILLAGE": "大園里",
      "NEIGHBORHOOD": "8鄰",
      "ROAD": "中山南路",
      "SECTION": "",
      "LANE": "",
      "ALLEY": "",
      "SUB_ALLEY": "",
      "TONG": "",
      "AREA": "",
      "NUMBER": "46號",
      "X": 121.197396,
      "Y": 25.063039
    },
    {
      "FULL_ADDR": "桃園市大園區海口里11鄰漁港路46號",
      "COUNTY": "桃園市",
      "TOWN": "大園區",
      "VILLAGE": "海口里",
      "NEIGHBORHOOD": "11鄰",
      "ROAD": "漁港路",
      "SECTION": "",
      "LANE": "",
      "ALLEY": "",
      "SUB_ALLEY": "",
      "TONG": "",
      "AREA": "",
      "NUMBER": "46號",
      "X": 121.241671,
      "Y": 25.109044
    },
    {
      "FULL_ADDR": "桃園市大園區溪海里13鄰功學路46號",
      "COUNTY": "桃園市",
      "TOWN": "大園區",
      "VILLAGE": "溪海里",
      "NEIGHBORHOOD": "13鄰",
      "ROAD": "功學路",
      "SECTION": "",
      "LANE": "",
      "ALLEY": "",
      "SUB_ALLEY": "",
      "TONG": "",
      "AREA": "",
      "NUMBER": "46號",
      "X": 121.183038,
      "Y": 25.045086
    },
    {
      "FULL_ADDR": "桃園市大園區大園里33鄰中正東路46號",
      "COUNTY": "桃園市",
      "TOWN": "大園區",
      "VILLAGE": "大園里",
      "NEIGHBORHOOD": "33鄰",
      "ROAD": "中正東路",
      "SECTION": "",
      "LANE": "",
      "ALLEY": "",
      "SUB_ALLEY": "",
      "TONG": "",
      "AREA": "",
      "NUMBER": "46號",
      "X": 121.198860,
      "Y": 25.063548
    },
    {
      "FULL_ADDR": "桃園市大園區海口里10鄰海沙路46號",
      "COUNTY": "桃園市",
      "TOWN": "大園區",
      "VILLAGE": "海口里",
      "NEIGHBORHOOD": "10鄰",
      "ROAD": "海沙路",
      "SECTION": "",
      "LANE": "",
      "ALLEY": "",
      "SUB_ALLEY": "",
      "TONG": "",
      "AREA": "",
      "NUMBER": "46號",
      "X": 121.240475,
      "Y": 25.108960
    },
    {
      "FULL_ADDR": "桃園市大園區竹圍里12鄰成功街46號",
      "COUNTY": "桃園市",
      "TOWN": "大園區",
      "VILLAGE": "竹圍里",
      "NEIGHBORHOOD": "12鄰",
      "ROAD": "成功街",
      "SECTION": "",
      "LANE": "",
      "ALLEY": "",
      "SUB_ALLEY": "",
      "TONG": "",
      "AREA": "",
      "NUMBER": "46號",
      "X": 121.239379,
      "Y": 25.101765
    },
    {
      "FULL_ADDR": "桃園市大園區大園里25鄰忠孝一街46號",
      "COUNTY": "桃園市",
      "TOWN": "大園區",
      "VILLAGE": "大園里",
      "NEIGHBORHOOD": "25鄰",
      "ROAD": "忠孝一街",
      "SECTION": "",
      "LANE": "",
      "ALLEY": "",
      "SUB_ALLEY": "",
      "TONG": "",
      "AREA": "",
      "NUMBER": "46號",
      "X": 121.199245,
      "Y": 25.066510
    }
  ]
}