<?xml version="1.0" encoding="utf-8"?>
<ArrayOfOpenData_7 xmlns:xsd="http://www.w3.org/2001/XMLSchema" xmlns:xsi="http://www.w3.org/2001/XMLSchema-instance">
  <OpenData_7>
    <宗祠基金會名稱>財團法人台北市陳悅記老師府基金會</宗祠基金會名稱>
    <行政區>臺北市</行政區>
    <地址>臺北市大同區重慶北路３段老師里9巷2號</地址>
    <電話>02-25917741.25917901</電話>
    <負責人>陳澤南</負責人>
    <WGS84X>121.513397216797</WGS84X>
    <WGS84Y>25.0740280151367</WGS84Y>
  </OpenData_7>
  <OpenData_7>
    <宗祠基金會名稱>財團法人宜蘭縣黃純善公基金會</宗祠基金會名稱>
    <行政區>宜蘭縣</行政區>
    <地址>宜蘭縣五結鄉五結路三段390號</地址>
    <電話>03-9567739</電話>
    <負責人>黃健司</負責人>
    <WGS84X>121.784515380859</WGS84X>
    <WGS84Y>24.683069229126</WGS84Y>
  </OpenData_7>
  <OpenData_7>
    <宗祠基金會名稱>財團法人高佛成基金會</宗祠基金會名稱>
    <行政區>臺北市</行政區>
    <地址>臺北市文山區溪口街1巷5號4樓</地址>
    <電話>02-86638912</電話>
    <負責人>高進財</負責人>
    <WGS84X>121.539901733398</WGS84X>
    <WGS84Y>24.9954795837402</WGS84Y>
  </OpenData_7>
  <OpenData_7>
    <宗祠基金會名稱>財團法人宜蘭縣林永記公廳基金會</宗祠基金會名稱>
    <行政區>宜蘭縣</行政區>
    <地址>宜蘭縣羅東鎮新群里月眉街630號</地址>
    <電話>03-9563547</電話>
    <負責人>林金鐘</負責人>
    <WGS84X>0</WGS84X>
    <WGS84Y>0</WGS84Y>
  </OpenData_7>
  <OpenData_7>
    <宗祠基金會名稱>財團法人金門縣一貫道崇德贊化基金會</宗祠基金會名稱>
    <行政區>金門縣</行政區>
    <地址>金門縣金湖鎮料羅里新塘27號</地址>
    <電話>02-28786161</電話>
    <負責人 />
    <WGS84X>0</WGS84X>
    <WGS84Y>0</WGS84Y>
  </OpenData_7>
  <OpenData_7>
    <宗祠基金會名稱>財團法人真提佛教基金會</宗祠基金會名稱>
    <行政區>臺中市</行政區>
    <地址>臺中市北屯區遼陽六街24號</地址>
    <電話>04-22453505</電話>
    <負責人>釋真提</負責人>
    <WGS84X>120.69556427002</WGS84X>
    <WGS84Y>24.1729431152344</WGS84Y>
  </OpenData_7>
  <OpenData_7>
    <宗祠基金會名稱>財團法人臺北市葛浦陽堂基金會</宗祠基金會名稱>
    <行政區>臺北市</行政區>
    <地址>臺北市中山區臺北市中山區吉林路75號</地址>
    <電話>02-25371115</電話>
    <負責人>葛台利</負責人>
    <WGS84X>0</WGS84X>
    <WGS84Y>0</WGS84Y>
  </OpenData_7>
  <OpenData_7>
    <宗祠基金會名稱>財團法人林三郎覺教基金會</宗祠基金會名稱>
    <行政區>高雄市</行政區>
    <地址>高雄市仁武區鳳仁路222號</地址>
    <電話>07-3711778</電話>
    <負責人>洪正威</負責人>
    <WGS84X>0</WGS84X>
    <WGS84Y>0</WGS84Y>
  </OpenData_7>
</ArrayOfOpenData_7>